fancymaps/__init__.py
fancymaps-0.1.22.dist-info/licenses/LICENSE.md
fancymaps-0.1.22.dist-info/METADATA
fancymaps-0.1.22.dist-info/WHEEL
fancymaps-0.1.22.dist-info/top_level.txt
fancymaps-0.1.22.dist-info/RECORD
