Metadata-Version: 2.4
Name: fancymaps
Version: 0.1.22
Summary: Visually appealing (diverging) colormaps
Author: Lennart Klebl
Author-email: lennart.klebl@rwth-aachen.de
License: GPLv3
Keywords: matplotlib
Classifier: License :: OSI Approved :: GNU General Public License v3 or later (GPLv3+)
Classifier: Programming Language :: Python :: 3
License-File: LICENSE.md
Requires-Dist: matplotlib>=3.2
Requires-Dist: setuptools>=30.3.0
Dynamic: description-content-type
Dynamic: license-file
Dynamic: requires-dist
Dynamic: summary
